LICENSE
fireproxng/__init__.py
fireproxng/__main__.py
fireproxng/lib/fire.py
fireproxng/utils/process.py
fireproxng-0.0.1.dist-info/entry_points.txt
fireproxng-0.0.1.dist-info/LICENSE
fireproxng-0.0.1.dist-info/WHEEL
fireproxng-0.0.1.dist-info/METADATA
fireproxng-0.0.1.dist-info/RECORD
