Metadata-Version: 2.1
Name: fireproxng
Version: 0.0.1
Summary: Next generation fireprox AWS API endpoint creation utility.
Home-page: https://github.com/puzzlepeaches/fireproxng
License: BSD 3-Clause License
Author: Nicholas Anastasi
Author-email: nanastasi@sprocketsecurity.com
Requires-Python: >=3.8,<4.0
Classifier: Environment :: Console
Classifier: License :: Other/Proprietary License
Classifier: Programming Language :: Python :: 3
Classifier: Programming Language :: Python :: 3.8
Classifier: Programming Language :: Python :: 3.9
Classifier: Programming Language :: Python :: 3.10
Classifier: Programming Language :: Python :: 3.11
Classifier: Programming Language :: Python :: 3
Classifier: Topic :: Security
Requires-Dist: boto3 (>=1.24.41,<2.0.0)
Requires-Dist: bs4 (>=0.0.1,<0.0.2)
Requires-Dist: click
Requires-Dist: click-extra (>=3.0.1,<4.0.0)
Requires-Dist: lxml (>=4.9.1,<5.0.0)
Requires-Dist: rich
Requires-Dist: tldextract (>=3.3.1,<4.0.0)
Requires-Dist: tzlocal (>=4.2,<5.0)
Requires-Dist: validators (>=0.20.0,<0.21.0)
Project-URL: Repository, https://github.com/puzzlepeaches/fireproxng
